autohell/__about__.py
autohell/__init__.py
autohell/__main__.py
autohell-0.1.1.dist-info/METADATA
autohell-0.1.1.dist-info/WHEEL
autohell-0.1.1.dist-info/entry_points.txt
autohell-0.1.1.dist-info/licenses/LICENSE
autohell-0.1.1.dist-info/RECORD
