Metadata-Version: 2.1
Name: autohell
Version: 0.1.1
Summary: Automatically controls your monitor's brightness
Project-URL: Documentation, https://github.com/pspeter/autohell#readme
Project-URL: Issues, https://github.com/pspeter/autohell/issues
Project-URL: Source, https://github.com/pspeter/autohell
Author-email: Peter Schmidbauer <peter@schmidbauer.at>
License-Expression: MIT
License-File: LICENSE
Classifier: Development Status :: 4 - Beta
Classifier: Programming Language :: Python
Classifier: Programming Language :: Python :: 3.11
Classifier: Programming Language :: Python :: 3.12
Classifier: Programming Language :: Python :: Implementation :: CPython
Requires-Python: >=3.11
Requires-Dist: screen-brightness-control
